uniparser/__init__.py
uniparser/__main__.py
uniparser/config.py
uniparser/crawler.py
uniparser/exceptions.py
uniparser/parsers.py
uniparser/utils.py
uniparser/webui.py
uniparser/fastapi_ui/__init__.py
uniparser/fastapi_ui/views.py
uniparser/static/uniparser.js
uniparser/static/uniparser.min.js
uniparser/templates/index.html
uniparser-3.0.3.dist-info/METADATA
uniparser-3.0.3.dist-info/WHEEL
uniparser-3.0.3.dist-info/top_level.txt
uniparser-3.0.3.dist-info/RECORD
