Metadata-Version: 2.4
Name: uniparser
Version: 3.0.3
Summary: Provide a universal solution for crawler platforms. Read more: https://github.com/ClericPy/uniparser.
Home-page: https://github.com/ClericPy/uniparser
Author: ClericPy
Author-email: clericpy@gmail.com
License: MIT License
Keywords: requests crawler parser tools universal lxml beautifulsoup bs4 jsonpath udf toml yaml
Platform: any
Classifier: License :: OSI Approved :: MIT License
Classifier: Programming Language :: Python
Classifier: Programming Language :: Python :: 3
Classifier: Programming Language :: Python :: 3.6
Classifier: Programming Language :: Python :: 3.7
Classifier: Programming Language :: Python :: 3.8
Classifier: Programming Language :: Python :: 3.9
Classifier: Programming Language :: Python :: 3.10
Requires-Dist: frequency-controller>=0.0.3
Requires-Dist: requests
Provides-Extra: requests
Requires-Dist: requests; extra == "requests"
Provides-Extra: httpx
Requires-Dist: httpx; extra == "httpx"
Provides-Extra: aiohttp
Requires-Dist: aiohttp; extra == "aiohttp"
Provides-Extra: torequests
Requires-Dist: torequests>=5.1.5; extra == "torequests"
Provides-Extra: webparsers
Requires-Dist: selectolax; extra == "webparsers"
Requires-Dist: jsonpath-rw-ext; extra == "webparsers"
Requires-Dist: objectpath; extra == "webparsers"
Requires-Dist: bs4; extra == "webparsers"
Requires-Dist: toml; extra == "webparsers"
Requires-Dist: pyyaml>=5.3; extra == "webparsers"
Requires-Dist: lxml; extra == "webparsers"
Requires-Dist: jmespath; extra == "webparsers"
Provides-Extra: all
Requires-Dist: requests; extra == "all"
Requires-Dist: httpx; extra == "all"
Requires-Dist: torequests>=5.1.5; extra == "all"
Requires-Dist: aiohttp; extra == "all"
Requires-Dist: selectolax; extra == "all"
Requires-Dist: jsonpath-rw-ext; extra == "all"
Requires-Dist: objectpath; extra == "all"
Requires-Dist: bs4; extra == "all"
Requires-Dist: toml; extra == "all"
Requires-Dist: pyyaml>=5.3; extra == "all"
Requires-Dist: lxml; extra == "all"
Requires-Dist: jmespath; extra == "all"
Provides-Extra: web
Requires-Dist: fastapi; extra == "web"
Requires-Dist: jinja2; extra == "web"
Requires-Dist: uvicorn; extra == "web"
Requires-Dist: uvloop; extra == "web"
Requires-Dist: aiofiles; extra == "web"
Dynamic: author
Dynamic: author-email
Dynamic: classifier
Dynamic: description
Dynamic: description-content-type
Dynamic: home-page
Dynamic: keywords
Dynamic: license
Dynamic: platform
Dynamic: provides-extra
Dynamic: requires-dist
Dynamic: summary
